<catalog>
  <product>
    <handle>alzador-bebesit-cs101</handle>
    <title>Asiento Elevador Booster Confort</title>
    <mas_detalles>Seguridad adecuada: Diseñado para niños de 15 a 36 kg, este alzador eleva al niño a la altura correcta para el uso adecuado del cinturón de seguridad del vehículo. Comodidad: Cuenta con apoyabrazos que proporcionan un soporte adicional, aumentando la comodidad durante los viajes. Fácil mantenimiento: La funda del asiento es lavable, lo que facilita su limpieza y mantenimiento.</mas_detalles>
  </product>
</catalog>
